odoo/addons/ssi_py3o/README.rst
odoo/addons/ssi_py3o/__init__.py
odoo/addons/ssi_py3o/__manifest__.py
odoo/addons/ssi_py3o/models/__init__.py
odoo/addons/ssi_py3o/models/ir_actions_report.py
odoo/addons/ssi_py3o/models/py3o_report.py
odoo/addons/ssi_py3o/static/description/icon.png
odoo/addons/ssi_py3o/views/ir_actions_report.xml
odoo14_addon_ssi_py3o-14.0.1.2.0.dist-info/METADATA
odoo14_addon_ssi_py3o-14.0.1.2.0.dist-info/WHEEL
odoo14_addon_ssi_py3o-14.0.1.2.0.dist-info/top_level.txt
odoo14_addon_ssi_py3o-14.0.1.2.0.dist-info/RECORD
