Metadata-Version: 2.1
Name: odoo14-addon-ssi_py3o
Version: 14.0.1.2.0
Summary: Py3o Extra
Home-page: https://simetri-sinergi.id
Author: OpenSynergy Indonesia, PT. Simetri Sinergi Indonesia
License: AGPL-3
Classifier: Programming Language :: Python
Classifier: Framework :: Odoo
Classifier: Framework :: Odoo :: 14.0
Classifier: License :: OSI Approved :: GNU Affero General Public License v3
Requires-Python: >=3.6
Requires-Dist: odoo14-addon-report-py3o
Requires-Dist: odoo<14.1dev,>=14.0a
